djangonginxremoteusermiddleware.py
setup.py
django_nginx_remote_user_middleware.egg-info/PKG-INFO
django_nginx_remote_user_middleware.egg-info/SOURCES.txt
django_nginx_remote_user_middleware.egg-info/dependency_links.txt
django_nginx_remote_user_middleware.egg-info/requires.txt
django_nginx_remote_user_middleware.egg-info/top_level.txt