Metadata-Version: 1.0
Name: django-nginx-remote-user-middleware
Version: 0.1
Summary: A drop-in middleware for Django which passes through REMOTE_USER variables set by reverse proxies
Home-page: UNKNOWN
Author: Chris Northwood
Author-email: chris@pling.org.uk
License: BSD
Platform: UNKNOWN
